{"body":"## Presentation\r\n\r\n**phpBeanstalkdAdmin** is a monitoring and administration interface for [Beanstalkd](http://kr.github.com/beanstalkd/).\r\n\r\nIt aims to support basic functionalities of Beanstalkd in order to help development and monitoring in production.\r\n\r\n![phpBeanstalkdAdmin screenshot](https://github.com/mnapoli/phpBeanstalkdAdmin/raw/master/docs/screenshot.png)\r\n\r\n## Installation\r\n\r\n### Prerequisites\r\n\r\n* Apache server\r\n* PHP version >= 5.3\r\n\r\n### Set up\r\n\r\n* Download the sources\r\n* Publish it on the Apache server. For example, add a symbolic link in the Apache root folder pointing to `phpBeanstalkdAdmin/public` folder.\r\n\r\nExample on linux or Mac OS X:\r\n\r\n    ln -s /path/to/phpBeanstalkdAdmin/public /var/www/phpbeanstalkdadmin\r\n\r\nphpBeanstalkdAdmin is now accessible at [http://localhost/phpbeanstalkdadmin/](http://localhost/phpbeanstalkdadmin/) (change \"localhost\" by your server name if necessary).\r\n\r\n## Development\r\n\r\nphpBeanstalkdAdmin started as a tool to support [Awespot](http://awespot.org/) development and administration.\r\n\r\nIt is based on [Pheanstalk](https://github.com/pda/pheanstalk/).\r\n\r\nYou can submit bugs or feature requests on [this page](https://github.com/mnapoli/phpBeanstalkdAdmin/issues/new).","google":"UA-15584647-11","note":"Don't delete this file! It's used internally to help with page regeneration.","tagline":"Monitoring and administration interface for Beanstalkd.","name":"phpBeanstalkdAdmin"}